identity_clustering/__init__.py
identity_clustering/_version.py
identity_clustering/cluster.py
identity_clustering/data_proc/__init__.py
identity_clustering/data_proc/jsonify.py
identity_clustering/data_proc/mds_proc.py
identity_clustering/dataset.py
identity_clustering/facedetector.py
identity_clustering/imports.py
identity_clustering/utils.py
identity_clustering/version.py
identity_clustering-2.2.4.dist-info/METADATA
identity_clustering-2.2.4.dist-info/WHEEL
identity_clustering-2.2.4.dist-info/RECORD
