Metadata-Version: 2.4
Name: identity_clustering
Version: 2.2.4
Summary: A package for video identity management, identity data storing and processing
Author: sanjithkumar
Author-email: sanjith.kumar@authenta.ai
Requires-Python: >=3.12,<4.0
Classifier: Programming Language :: Python :: 3
Classifier: Programming Language :: Python :: 3.12
Classifier: Programming Language :: Python :: 3.13
Classifier: Programming Language :: Python :: 3.14
Requires-Dist: cython (>=3.0.11,<4.0.0)
Requires-Dist: facenet-pytorch (>=2.6.0,<3.0.0)
Requires-Dist: insightface (>=0.7.3,<0.8.0)
Requires-Dist: jupyterlab (>=4.3.3,<5.0.0)
Requires-Dist: onnxruntime (==1.22.0)
Requires-Dist: opencv-python (>=4.10.0.84,<5.0.0.0)
Requires-Dist: pytest (>=8.3.4,<9.0.0)
